[{"team_name": "Player's Team", "user": "alpha6et", "played": 192, "wins": 93, "draws": 31, "losses": 68, "points": 310, "gf": 390, "ga": 349, "gd": 41}, {"team_name": "most atrocious exhibition", "user": "the1n1ly", "played": 192, "wins": 79, "draws": 32, "losses": 81, "points": 269, "gf": 367, "ga": 372, "gd": -5, "color": "#FF0000"}, {"team_name": "Player's Team", "user": "ddqwlgcg_84775", "played": 192, "wins": 78, "draws": 26, "losses": 88, "points": 260, "gf": 372, "ga": 370, "gd": 2, "color": "#FF00FF"}, {"team_name": "Player's Team", "user": "gxlorenzz", "played": 192, "wins": 79, "draws": 21, "losses": 92, "points": 258, "gf": 357, "ga": 395, "gd": -38, "color": "#0000FF"}]